COPYING
MANIFEST.in
README.rst
bootstrap.py
buildout.cfg
setup.py
docs/conf.py
docs/index.rst
docs/roc.png
xbob/__init__.py
xbob.paper.example.egg-info/PKG-INFO
xbob.paper.example.egg-info/SOURCES.txt
xbob.paper.example.egg-info/dependency_links.txt
xbob.paper.example.egg-info/entry_points.txt
xbob.paper.example.egg-info/namespace_packages.txt
xbob.paper.example.egg-info/requires.txt
xbob.paper.example.egg-info/top_level.txt
xbob/paper/__init__.py
xbob/paper/example/__init__.py
xbob/paper/example/test.py
xbob/paper/example/utils.py
xbob/paper/example/scripts/__init__.py
xbob/paper/example/scripts/evaluate.py
xbob/paper/example/scripts/lbfgs_training.py
xbob/paper/example/scripts/plot.py
xbob/paper/example/scripts/rprop_training.py